djangocamera/__init__.py
djangocamera/camera.py
djangocamera/streaming.py
djangocamera-0.0.1.dist-info/LICENSE
djangocamera-0.0.1.dist-info/METADATA
djangocamera-0.0.1.dist-info/WHEEL
djangocamera-0.0.1.dist-info/top_level.txt
djangocamera-0.0.1.dist-info/RECORD
