Metadata-Version: 2.1
Name: djangocamera
Version: 0.0.1
Summary: Accessing camera on Django Webframework
Home-page: UNKNOWN
Author: Naman Goyal (Naman82)
Author-email: <namangoyal.developer@gmail.com>
License: UNKNOWN
Keywords: django,python,video,stream,video stream,camera stream,django camera,django video
Platform: UNKNOWN
Classifier: Development Status :: 1 - Planning
Classifier: Intended Audience :: Developers
Classifier: Programming Language :: Python :: 3
Classifier: Operating System :: Unix
Classifier: Operating System :: MacOS :: MacOS X
Classifier: Operating System :: Microsoft :: Windows
License-File: LICENSE
Requires-Dist: opencv-python
Requires-Dist: django
